vrt_lss_account/__init__.py
vrt_lss_account/api_client.py
vrt_lss_account/api_response.py
vrt_lss_account/configuration.py
vrt_lss_account/exceptions.py
vrt_lss_account/py.typed
vrt_lss_account/rest.py
vrt_lss_account/api/__init__.py
vrt_lss_account/api/audit_api.py
vrt_lss_account/api/auth_api.py
vrt_lss_account/api/data_api.py
vrt_lss_account/api/info_api.py
vrt_lss_account/api/quota_api.py
vrt_lss_account/api/statistics_api.py
vrt_lss_account/api/system_api.py
vrt_lss_account/models/__init__.py
vrt_lss_account/models/account_audit_result.py
vrt_lss_account/models/attribute.py
vrt_lss_account/models/audit_action.py
vrt_lss_account/models/audit_action_statistics.py
vrt_lss_account/models/audit_counters.py
vrt_lss_account/models/audit_counters_detail.py
vrt_lss_account/models/calculation_info.py
vrt_lss_account/models/calculation_status.py
vrt_lss_account/models/check_result.py
vrt_lss_account/models/date_statistics.py
vrt_lss_account/models/flow_stage.py
vrt_lss_account/models/flow_type.py
vrt_lss_account/models/general400.py
vrt_lss_account/models/general402.py
vrt_lss_account/models/general403.py
vrt_lss_account/models/general404.py
vrt_lss_account/models/general404_detail.py
vrt_lss_account/models/general429.py
vrt_lss_account/models/general500.py
vrt_lss_account/models/info_change_request.py
vrt_lss_account/models/password_change_request.py
vrt_lss_account/models/process_quota.py
vrt_lss_account/models/process_statistics.py
vrt_lss_account/models/process_type.py
vrt_lss_account/models/quota_base.py
vrt_lss_account/models/quotas_result.py
vrt_lss_account/models/schema_error.py
vrt_lss_account/models/service.py
vrt_lss_account/models/service_quota.py
vrt_lss_account/models/service_statistics.py
vrt_lss_account/models/token_request.py
vrt_lss_account/models/token_validation_result.py
vrt_lss_account/models/tracedata.py
vrt_lss_account/models/user.py
vrt_lss_account/models/user_role.py
vrt_lss_account/models/user_statistics.py
vrt_lss_account-7.29.3120.dist-info/METADATA
vrt_lss_account-7.29.3120.dist-info/WHEEL
vrt_lss_account-7.29.3120.dist-info/top_level.txt
vrt_lss_account-7.29.3120.dist-info/RECORD
